README.rst
setup.py
api/__init__.py
api/api_client.py
api/utils.py
sangfor_sslvpn_api.egg-info/PKG-INFO
sangfor_sslvpn_api.egg-info/SOURCES.txt
sangfor_sslvpn_api.egg-info/dependency_links.txt
sangfor_sslvpn_api.egg-info/top_level.txt