Metadata-Version: 1.1
Name: sangfor-sslvpn-api
Version: 1.0
Summary: sangfor_sslvpn_api
Home-page: https://github.com/Kac001/sangfor_sslvpn_api
Author: Kac001
Author-email: jleung@qq.com
License: MIT License
Platform: all
Classifier: Development Status :: 4 - Beta
Classifier: Operating System :: OS Independent
Classifier: Intended Audience :: Developers
Classifier: License :: OSI Approved :: BSD License
Classifier: Programming Language :: Python :: 3.6
Classifier: Programming Language :: Python :: 3.7
Classifier: Programming Language :: Python :: 3.8
Classifier: Programming Language :: Python :: 3.9
Classifier: Topic :: Software Development :: Libraries
